chatgptcode/__main__.py
chatgptcode/chat_gpt.py
chatgptcode/chat_interface.py
chatgptcode/cli.py
chatgptcode-0.1.0.dist-info/METADATA
chatgptcode-0.1.0.dist-info/LICENSE
chatgptcode-0.1.0.dist-info/WHEEL
chatgptcode-0.1.0.dist-info/RECORD
