Metadata-Version: 2.1
Name: chatgptcode
Version: 0.1.0
Summary: A command line tool for interacting with ChatGPT to help with development
License: MIT
Author: Brian Moody
Author-email: brian.kmdy@gmail.com
Requires-Python: >=3.7,<4.0
Classifier: License :: OSI Approved :: MIT License
Classifier: Programming Language :: Python :: 3
Classifier: Programming Language :: Python :: 3.7
Classifier: Programming Language :: Python :: 3.8
Classifier: Programming Language :: Python :: 3.9
Classifier: Programming Language :: Python :: 3.10
Classifier: Programming Language :: Python :: 3.11
Requires-Dist: click (>=8.1.3,<9.0.0)
Requires-Dist: pygments (>=2.14.0,<3.0.0)
Requires-Dist: revChatGPT (>=0.3.1,<0.4.0)
Requires-Dist: termcolor (>=2.2.0,<3.0.0)
Requires-Dist: twocaptcha (>=0.0.1,<0.0.2)
